{"word_id": "4810", "lemma": "སུ་", "meanings": {"1365": {"meaning": "བྱ་བ་བྱེད་སའི་ཡུལ་སྟོན་བྱེད་ཀྱི་ཕྲད། རྗེས་འཇུག་ས་ཡི་རྗེས་སུ་སྦྱར་དགོས།", "examples": {"1": "ཤར་ཕྱོགས་སུ་འགྲོ།"}, "pos": "ཚབ་ཚིག"}, "1366": {"meaning": "བྱ་བའི་དགོས་ཆེད་སྟོན་བྱེད་ཀྱི་ཕྲད། རྗེས་འཇུག་ས་ཡི་རྗེས་སུ་སྦྱར་དགོས།", "examples": {"1": "ཟས་སུ་རྩམ་པ་ཟོས།"}, "pos": "ཚབ་ཚིག"}, "1367": {"meaning": "གང་ཞིག་གང་ན་ཡོད་པ་སྟོན་བྱེད་ཀྱི་ཕྲད། རྗེས་འཇུག་ས་ཡི་རྗེས་སུ་སྦྱར་དགོས།", "examples": {"1": "རང་གནས་སུ་ཡོད།"}, "pos": "ཚབ་ཚིག"}, "1368": {"meaning": "བྱ་བ་དང་ལས་གཉིས་ངོ་བོ་གཅིག་ཏུ་སྟོན་བྱེད་ཀྱི་ཕྲད། རྗེས་འཇུག་ས་ཡི་རྗེས་སུ་སྦྱར་དགོས།", "examples": {"1": "ཇེ་ལེགས་སུ་སོང་།"}, "pos": "ཚབ་ཚིག"}, "1369": {"meaning": "བྱ་བའི་དུས་སྟོན་བྱེད་ཀྱི་ཕྲད། རྗེས་འཇུག་ས་ཡི་རྗེས་སུ་སྦྱར་དགོས།", "examples": {"1": "མཚན་དུས་སུ་གཉིད།"}, "pos": "ཚབ་ཚིག"}, "1370": {"meaning": "མི་གང་ཡང་རུང་བ་ཞིག་གི་མིང་གི་ཚབ།", "examples": {"1": "ཁང་པའི་ནང་ལ་སུ་ཡོད།"}, "pos": "ཚབ་ཚིག"}}, "level": "A0"}