{"word_id": "10908", "lemma": "བརྩེད་", "meanings": {"8161": {"meaning": "རྟ་དང་དྲེལ་སོགས་བཞོན་ནས་ཡུན་རིང་འགྲོ་སྐབས། རྨིག་པའི་སྣེ་ཟད་དེ་ཤ་ལ་ཐུག་པར་ཉེ་དུས། ས་ལ་ཐུག་པར་མི་བཟོད་པར་གྱུར་པ་སྟེ།", "examples": {"1": "རྟ་བརྩེད་ནས་ཉིན་འགའ་འགྲོ་མ་ཐུབ་ལྟ་བུ།"}, "pos": "བྱ་ཚིག"}, "8162": {"meaning": "འོད་ཆེ་དྲགས་ནས་མིག་གིས་ལྟ་མི་བཟོད་པར་གྱུར་པ་སྟེ།", "examples": {"1": "ཉི་མ་ལ་བལྟས་ན་མིག་བརྩེད་ལྟ་བུ།"}, "pos": "བྱ་ཚིག"}, "8163": {"meaning": "སྐྱུར་མོའི་རིགས་ཟ་འཐུང་བྱེད་རྒྱུ་མང་དྲགས་ནས་སོ་ལ་ན་ཟུག་གཏོང་བ་སྟེ།", "examples": {"1": "སོ་བརྩེད་ནས་བག་ལེབ་ཟ་མ་ཐུབ་ལྟ་བུ།"}, "pos": "བྱ་ཚིག"}, "8164": {"meaning": "ཞེད་སྣང་སྐྱེས་པ་འམ་དངངས་འཚབ་ལངས་པ་སྟེ།", "examples": {"1": "བུ་ཕྲུག་ས་མཐར་སོང་བས་ཨ་མའི་སེམས་བརྩེད་ལྟ་བུ།"}, "pos": "བྱ་ཚིག"}, "8165": {"meaning": "སྡུག་བསྔལ་དང་གནས་སྟངས་སོགས་ཡ་ང་ཞིང་ཉམ་ཐག་པ་མཐོང་ནས་ཤས་མི་བཟོད་པའི་སྙིང་རྗེ་འམ་སེམས་ཚོར་དྲག་པོ་བྱུང་བ་སྟེ།", "examples": {"1": "ཤ་བརྩེད་ནས་ལྟ་ཐུབ་ཀྱི་མི་འདུག་ལྟ་བུ།"}, "pos": "བྱ་ཚིག"}}, "level": "C2"}